shrillecho/__init__.py
shrillecho/api/__init__.py
shrillecho/api/api_client.py
shrillecho/api/api_request_handler.py
shrillecho/api/auth/__init__.py
shrillecho/api/auth/oauth.py
shrillecho/api/endpoints/__init__.py
shrillecho/api/endpoints/albums.py
shrillecho/api/endpoints/artists.py
shrillecho/api/endpoints/endpoint.py
shrillecho/api/endpoints/endpoint_urls.py
shrillecho/api/endpoints/follow.py
shrillecho/api/endpoints/player.py
shrillecho/api/endpoints/playlists.py
shrillecho/api/endpoints/search.py
shrillecho/api/endpoints/tracks.py
shrillecho/api/endpoints/users.py
shrillecho/api/task_scheduler.py
shrillecho/controllers/__init__.py
shrillecho/controllers/album_controller.py
shrillecho/controllers/artist_controller.py
shrillecho/controllers/player_controller.py
shrillecho/controllers/playlist_controller.py
shrillecho/controllers/track_controller.py
shrillecho/controllers/tracks_controller.py
shrillecho/controllers/user_controller.py
shrillecho/discovery/artist_crawler.py
shrillecho/discovery/song_similarity.py
shrillecho/types/__init__.py
shrillecho/types/album_types.py
shrillecho/types/archive_delete/all.py
shrillecho/types/artist_types.py
shrillecho/types/base_types.py
shrillecho/types/component_types.py
shrillecho/types/player_types.py
shrillecho/types/playlist_types.py
shrillecho/types/search_types.py
shrillecho/types/soundcloud_types.py
shrillecho/types/track_types.py
shrillecho/types/user_types.py
shrillecho/utility/__init__.py
shrillecho/utility/album_utils.py
shrillecho/utility/artist_utils.py
shrillecho/utility/cache.py
shrillecho/utility/general_utility.py
shrillecho/utility/neo4j.py
shrillecho/utility/track_utils.py
shrillecho-1.1.11.dist-info/METADATA
shrillecho-1.1.11.dist-info/WHEEL
shrillecho-1.1.11.dist-info/RECORD
