Metadata-Version: 2.1
Name: shrillecho
Version: 1.1.11
Summary: Music Tool
Author: simon balfe
Author-email: sbmain17@gmail.com
Requires-Python: >=3.11,<4.0
Classifier: Programming Language :: Python :: 3
Classifier: Programming Language :: Python :: 3.11
Classifier: Programming Language :: Python :: 3.12
Requires-Dist: anyio (>=3.7.1,<3.8.0)
Requires-Dist: attrs (>=23.1.0,<23.2.0)
Requires-Dist: cleo (>=2.1.0,<2.2.0)
Requires-Dist: crashtest (>=0.4.1,<0.5.0)
Requires-Dist: dnspython (>=2.4.2,<2.5.0)
Requires-Dist: esper (>=3.0,<4.0)
Requires-Dist: fastclasses-json (>=0.7.0,<0.8.0)
Requires-Dist: h11 (>=0.14.0,<0.15.0)
Requires-Dist: httpcore (>=1.0.1,<1.1.0)
Requires-Dist: httpx (>=0.25.1,<0.26.0)
Requires-Dist: idna (>=3.4,<4.0)
Requires-Dist: jinja2 (>=3.1.2,<3.2.0)
Requires-Dist: numpy (>=1.26.4,<1.27.0)
Requires-Dist: pillow (>=10.2.0,<10.3.0)
Requires-Dist: pip (>=23.2.1,<23.3.0)
Requires-Dist: psycopg2 (>=2.9.9,<2.10.0)
Requires-Dist: pymongo (>=4.8.0,<5.0.0)
Requires-Dist: python-dotenv (>=1.0.0,<1.1.0)
Requires-Dist: redis (>=5.0.1,<5.1.0)
Requires-Dist: requests (>=2.31.0,<2.32.0)
Requires-Dist: setuptools (>=65.5.0,<65.6.0)
Requires-Dist: spotipy (>=2.23.0,<2.24.0)
Requires-Dist: trio (>=0.22.2,<0.23.0)
